{"cameraMode":{"drawMode":0,"name":"Shaded","section":"Shading Mode"},"sceneLighting":false,"audioPlay":false,"sceneViewState":{"m_AlwaysRefresh":false,"showFog":true,"showSkybox":false,"showFlares":true,"showImageEffects":true,"showParticleSystems":true,"showVisualEffectGraphs":true,"m_FxEnabled":true},"in2DMode":false,"pivot":{"x":2.8499999046325685,"y":90.75126647949219,"z":-1.2899999618530274},"rotation":{"x":-0.16533303260803224,"y":-0.77325838804245,"z":0.22247877717018128,"w":-0.5706024169921875},"size":5.424298286437988,"orthographic":false}